defusedxml-stubs/ElementTree.pyi
defusedxml-stubs/METADATA.toml
defusedxml-stubs/__init__.pyi
defusedxml-stubs/cElementTree.pyi
defusedxml-stubs/common.pyi
defusedxml-stubs/expatbuilder.pyi
defusedxml-stubs/expatreader.pyi
defusedxml-stubs/lxml.pyi
defusedxml-stubs/minidom.pyi
defusedxml-stubs/pulldom.pyi
defusedxml-stubs/py.typed
defusedxml-stubs/sax.pyi
defusedxml-stubs/xmlrpc.pyi
types_defusedxml-0.7.0.20250809.dist-info/licenses/LICENSE
types_defusedxml-0.7.0.20250809.dist-info/METADATA
types_defusedxml-0.7.0.20250809.dist-info/WHEEL
types_defusedxml-0.7.0.20250809.dist-info/top_level.txt
types_defusedxml-0.7.0.20250809.dist-info/RECORD
